{
  "type": "footer",
  "name": "Footer group",
  "sections": {
    "16921040486797a197": {
      "type": "apps",
      "settings": {
        "full_width": true,
        "remove_vertical_spacing": false,
        "remove_horizontal_spacing": false,
        "background": "",
        "background_gradient": "",
        "text_color": "",
        "enable_review_integration": true,
        "review_header_gradient": "linear-gradient(135deg, rgba(255, 194, 102, 1), rgba(255, 163, 26, 1) 100%)",
        "review_header_text_color": "#000000",
        "review_button_background": "#000000",
        "review_button_text_color": "#ffffff"
      }
    },
    "text-with-icons": {
      "type": "text-with-icons",
      "blocks": {
        "free-shipping": {
          "type": "item",
          "settings": {
            "icon": "picto-box",
            "mobile_icon_width": 24,
            "icon_width": 24,
            "icon_background_type": "none",
            "icon_background": "",
            "icon_color": "",
            "title": "Free shipping",
            "content": "<p>Tell your customers about your shipping offer.<\/p>"
          }
        },
        "customer-support": {
          "type": "item",
          "settings": {
            "icon": "picto-customer-support",
            "mobile_icon_width": 24,
            "icon_width": 24,
            "icon_background_type": "none",
            "icon_background": "",
            "icon_color": "",
            "title": "Customer service",
            "content": "<p>Tell your customers how they can reach you.<\/p>"
          }
        },
        "discount": {
          "type": "item",
          "settings": {
            "icon": "picto-coupon",
            "mobile_icon_width": 24,
            "icon_width": 24,
            "icon_background_type": "none",
            "icon_background": "",
            "icon_color": "",
            "title": "Refer a friend",
            "content": "<p>Tell your customers about your promotional offers.<\/p>"
          }
        },
        "payment": {
          "type": "item",
          "settings": {
            "icon": "picto-lock",
            "mobile_icon_width": 24,
            "icon_width": 24,
            "icon_background_type": "none",
            "icon_background": "",
            "icon_color": "",
            "title": "Secure payment",
            "content": "<p>Tel your customers about your payment methods.<\/p>"
          }
        },
        "bff30cd9-fc82-49cb-8321-5a592030eb9f": {
          "type": "item",
          "settings": {
            "icon": "picto-customer-support",
            "mobile_icon_width": 24,
            "icon_width": 32,
            "icon_background_type": "circle",
            "icon_background": "",
            "icon_color": "",
            "title": "Heading",
            "content": "<p>Short content about your store<\/p>"
          }
        }
      },
      "block_order": [
        "free-shipping",
        "customer-support",
        "discount",
        "payment",
        "bff30cd9-fc82-49cb-8321-5a592030eb9f"
      ],
      "disabled": true,
      "settings": {
        "full_width": true,
        "stack_on_mobile": false,
        "title": "",
        "heading_tag": "h6",
        "text_alignment": "center",
        "icon_spacing": "small",
        "background": "",
        "background_gradient": "",
        "text_color": ""
      }
    },
    "16989710070f532485": {
      "type": "apps",
      "blocks": {
        "2da11bf3-5459-4046-b909-9ffcb8962061": {
          "type": "shopify:\/\/apps\/forms\/blocks\/inline\/8744a304-fcb1-4347-b211-bb6b4759a76a",
          "settings": {
            "form_id": "",
            "text_color": "#202020",
            "button_background_color": "#202020",
            "button_label_color": "#FFFFFF",
            "links_color": "#1878B9",
            "errors_color": "#E02229",
            "text_alignment": "center",
            "form_alignment": "center",
            "padding_top": 0,
            "padding_bottom": 0,
            "padding_right": 0,
            "padding_left": 0
          }
        }
      },
      "block_order": [
        "2da11bf3-5459-4046-b909-9ffcb8962061"
      ],
      "settings": {
        "full_width": true,
        "remove_vertical_spacing": false,
        "remove_horizontal_spacing": false,
        "background": "",
        "background_gradient": "",
        "text_color": "",
        "enable_review_integration": true,
        "review_header_gradient": "linear-gradient(135deg, rgba(255, 194, 102, 1), rgba(255, 163, 26, 1) 100%)",
        "review_header_text_color": "#000000",
        "review_button_background": "#000000",
        "review_button_text_color": "#ffffff"
      }
    },
    "footer": {
      "type": "footer",
      "blocks": {
        "newsletter": {
          "type": "newsletter",
          "settings": {
            "image_width": 150,
            "heading_size": "h5",
            "title": "Join the Trak Racer community!",
            "content": "<p>Subscribe to get unique offers and community content!<\/p>"
          }
        },
        "links": {
          "type": "links",
          "settings": {
            "menu": "general",
            "show_menu_title": true
          }
        },
        "b04f5f50-51db-467b-9546-223920775c32": {
          "type": "links",
          "settings": {
            "menu": "support",
            "show_menu_title": true
          }
        },
        "1b353c78-1819-4f33-82ce-ef2f94b95921": {
          "type": "links",
          "settings": {
            "menu": "service",
            "show_menu_title": true
          }
        },
        "2c83b313-91fb-438b-a3d7-53ef6668cbd9": {
          "type": "text",
          "settings": {
            "title": "Customer Support",
            "content": "<p>For SALES email us at <strong>sales@trakracer.com.au<\/strong><\/p><p>For SUPPORT email us at <strong>support@trakracer.com.au<\/strong><\/p>",
            "enable_follow_on_shop": false
          }
        }
      },
      "block_order": [
        "newsletter",
        "links",
        "b04f5f50-51db-467b-9546-223920775c32",
        "1b353c78-1819-4f33-82ce-ef2f94b95921",
        "2c83b313-91fb-438b-a3d7-53ef6668cbd9"
      ],
      "custom_css": [

      ],
      "settings": {
        "show_social_media": true,
        "show_payment_icons": true,
        "show_country_selector": true,
        "show_country_flag": true,
        "show_country_name": true,
        "show_locale_selector": true
      }
    }
  },
  "order": [
    "16921040486797a197",
    "text-with-icons",
    "16989710070f532485",
    "footer"
  ]
}
